{
   "participant": 9, 
   "tasks": {
      "1": [
         {
            "draw": null, 
            "event_type": "drag", 
            "example": false, 
            "fingers": 1, 
            "hands": 1, 
            "no_contact": false, 
            "objects": [
               "robots"
            ], 
            "time": 164.27, 
            "write": null
         }, 
         {
            "draw": null, 
            "event_type": "drag", 
            "example": false, 
            "fingers": 2, 
            "hands": 1, 
            "no_contact": false, 
            "objects": [
               "robots"
            ], 
            "time": 164.27, 
            "write": null
         }, 
         {
            "draw": null, 
            "event_type": "drag", 
            "example": false, 
            "fingers": 1, 
            "hands": 1, 
            "no_contact": false, 
            "objects": [
               "robots"
            ], 
            "time": 169.04, 
            "write": null
         }, 
         {
            "description": [
               "none", 
               "of", 
               "the", 
               "drag", 
               "gestures", 
               "left", 
               "area", 
               "of", 
               "robots.", 
               "User", 
               "may", 
               "have", 
               "been", 
               "expecting", 
               "UI", 
               "to", 
               "react"
            ], 
            "event_type": "memo"
         }, 
         {
            "draw": null, 
            "event_type": "drag", 
            "example": false, 
            "fingers": 1, 
            "hands": 1, 
            "no_contact": false, 
            "objects": [
               "area", 
               "a", 
               "towards", 
               "robots"
            ], 
            "time": 177.73, 
            "write": null
         }, 
         {
            "draw": null, 
            "event_type": "drag", 
            "example": false, 
            "fingers": 1, 
            "hands": 1, 
            "no_contact": false, 
            "objects": [
               "robots"
            ], 
            "time": 180.44, 
            "write": null
         }, 
         {
            "command": [
               "\"move\""
            ], 
            "event_type": "voice_command", 
            "time": 199.13
         }, 
         {
            "command": [
               "\"move", 
               "to", 
               "area", 
               "a\""
            ], 
            "event_type": "voice_command", 
            "time": 206.15
         }
      ], 
      "10": [
         {
            "command": [
               "robots", 
               "form", 
               "a", 
               "single", 
               "line", 
               "with", 
               "the", 
               "back", 
               "of", 
               "one", 
               "robot", 
               "facing", 
               "the", 
               "front", 
               "of", 
               "another"
            ], 
            "event_type": "voice_command", 
            "time": 396.49
         }, 
         {
            "description": [
               "prompted", 
               "user", 
               "to", 
               "specify", 
               "where", 
               "line", 
               "was", 
               "in", 
               "the", 
               "space"
            ], 
            "event_type": "memo"
         }, 
         {
            "description": [
               "user", 
               "said", 
               "they", 
               "would", 
               "rather", 
               "have", 
               "it", 
               "be", 
               "\"in", 
               "the", 
               "center\"", 
               "but", 
               "didn't", 
               "show", 
               "how", 
               "they", 
               "would", 
               "show", 
               "the", 
               "systme", 
               "that"
            ], 
            "event_type": "memo"
         }
      ], 
      "11": [
         {
            "command": [
               "robots", 
               "form", 
               "a", 
               "square", 
               "with", 
               "the", 
               "smallest", 
               "area"
            ], 
            "event_type": "voice_command", 
            "time": 435.24
         }
      ], 
      "12": [
         {
            "command": [
               "robots", 
               "position", 
               "yourselves", 
               "around", 
               "the", 
               "crate", 
               "equally", 
               "and", 
               "move", 
               "it", 
               "to", 
               "area", 
               "a"
            ], 
            "event_type": "voice_command", 
            "time": 452.86
         }, 
         {
            "description": [
               "command", 
               "still", 
               "has", 
               "a", 
               "staging", 
               "phase", 
               "and", 
               "a", 
               "movement", 
               "phase"
            ], 
            "event_type": "memo"
         }
      ], 
      "13": [
         {
            "command": [
               "robots", 
               "position", 
               "yourselves", 
               "around", 
               "the", 
               "crate", 
               "on", 
               "three", 
               "of", 
               "the", 
               "sides", 
               "which", 
               "are", 
               "not", 
               "facing", 
               "area", 
               "a", 
               "and", 
               "move", 
               "the", 
               "crate", 
               "to", 
               "area", 
               "a"
            ], 
            "event_type": "voice_command", 
            "time": 480.88
         }
      ], 
      "14": [
         {
            "command": [
               "robots", 
               "detect", 
               "heat", 
               "release", 
               "rate", 
               "and", 
               "if", 
               "heat", 
               "release", 
               "rate", 
               "is", 
               "above", 
               "the", 
               "minimum", 
               "rate", 
               "please", 
               "move", 
               "to", 
               "the", 
               "corner"
            ], 
            "event_type": "voice_command", 
            "time": 510.54
         }, 
         {
            "description": [
               "because", 
               "the", 
               "defective", 
               "robot", 
               "is", 
               "apparently", 
               "smoking.", 
               "Maybe", 
               "I", 
               "should", 
               "have", 
               "made", 
               "it", 
               "a", 
               "non-obvious", 
               "type", 
               "of", 
               "defect"
            ], 
            "event_type": "memo"
         }
      ], 
      "15": [
         {
            "command": [
               "robots", 
               "detect", 
               "total", 
               "heat", 
               "release", 
               "rate", 
               "and", 
               "and", 
               "if", 
               "heat", 
               "release", 
               "rate", 
               "is", 
               "above", 
               "a", 
               "minimum", 
               "level", 
               "please", 
               "move", 
               "to", 
               "the", 
               "side", 
               "away", 
               "from", 
               "all", 
               "the", 
               "other", 
               "robots"
            ], 
            "event_type": "voice_command", 
            "time": 541.55
         }
      ], 
      "16": [
         {
            "command": [
               "robots", 
               "align", 
               "yourselves", 
               "in", 
               "a", 
               "straight", 
               "line", 
               "with", 
               "the", 
               "back", 
               "of", 
               "each", 
               "robot", 
               "facing", 
               "the", 
               "front", 
               "of", 
               "the", 
               "other", 
               "and", 
               "move", 
               "across", 
               "the", 
               "screen"
            ], 
            "event_type": "voice_command", 
            "time": 570.05
         }
      ], 
      "17": [
         {
            "command": [
               "robots", 
               "position", 
               "yourselves", 
               "in", 
               "a", 
               "straight", 
               "line", 
               "along", 
               "the", 
               "edge", 
               "of", 
               "area", 
               "a", 
               "and", 
               "patrol", 
               "across", 
               "area", 
               "a"
            ], 
            "event_type": "voice_command", 
            "time": 591.77
         }, 
         {
            "description": [
               "user", 
               "clarified", 
               "that", 
               "this", 
               "should", 
               "go", 
               "around", 
               "the", 
               "perimeter", 
               "rather", 
               "than", 
               "sweep", 
               "across", 
               "when", 
               "asked"
            ], 
            "event_type": "memo"
         }
      ], 
      "18": [
         {
            "command": [
               "robots", 
               "disperse", 
               "over", 
               "the", 
               "screen", 
               "area", 
               "without", 
               "exiting", 
               "the", 
               "border"
            ], 
            "event_type": "voice_command", 
            "time": 621.03
         }, 
         {
            "description": [
               "commands", 
               "that", 
               "directly", 
               "reference", 
               "the", 
               "screen", 
               "are", 
               "more", 
               "obvious", 
               "in", 
               "voice", 
               "than", 
               "in", 
               "gestures.", 
               "\"fog", 
               "of", 
               "war\"", 
               "style", 
               "UI", 
               "complicates", 
               "this", 
               "some."
            ], 
            "event_type": "memo"
         }
      ], 
      "2": [
         {
            "command": [
               "jump", 
               "over", 
               "the", 
               "wall", 
               "and", 
               "move", 
               "to", 
               "area", 
               "a"
            ], 
            "event_type": "voice_command", 
            "time": 226.07
         }
      ], 
      "3": [
         {
            "command": [
               "stop", 
               "where", 
               "you", 
               "are"
            ], 
            "event_type": "voice_command", 
            "time": 239.1
         }
      ], 
      "4": [
         {
            "command": [
               "half", 
               "of", 
               "the", 
               "robots", 
               "move", 
               "around", 
               "the", 
               "wall", 
               "and", 
               "go", 
               "to", 
               "area", 
               "a"
            ], 
            "event_type": "voice_command", 
            "time": 262.03
         }, 
         {
            "command": [
               "and", 
               "the", 
               "other", 
               "half", 
               "move", 
               "around", 
               "the", 
               "wall", 
               "and", 
               "go", 
               "to", 
               "area", 
               "b"
            ], 
            "event_type": "voice_command", 
            "time": 264.62
         }
      ], 
      "5": [
         {
            "command": [
               "orange", 
               "robots", 
               "move", 
               "around", 
               "the", 
               "wall", 
               "and", 
               "proceed", 
               "to", 
               "area", 
               "b"
            ], 
            "event_type": "voice_command", 
            "time": 282.31
         }, 
         {
            "command": [
               "while", 
               "the", 
               "red", 
               "robots", 
               "move", 
               "around", 
               "the", 
               "wall", 
               "and", 
               "proceed", 
               "to", 
               "area", 
               "a"
            ], 
            "event_type": "voice_command", 
            "time": 287.41
         }
      ], 
      "6": [
         {
            "command": [
               "orange", 
               "robots", 
               "move", 
               "around", 
               "the", 
               "wall", 
               "and", 
               "proceed", 
               "to", 
               "area", 
               "a"
            ], 
            "event_type": "voice_command", 
            "time": 299.78
         }, 
         {
            "command": [
               "and", 
               "red", 
               "robots", 
               "move", 
               "around", 
               "the", 
               "wall", 
               "and", 
               "proceed", 
               "to", 
               "area", 
               "b"
            ], 
            "event_type": "voice_command", 
            "time": 303.69
         }, 
         {
            "description": [
               "voice", 
               "commands", 
               "are", 
               "very", 
               "fast", 
               "to", 
               "issue,", 
               "especially", 
               "to", 
               "addressable", 
               "groups"
            ], 
            "event_type": "memo"
         }
      ], 
      "7": [
         {
            "command": [
               "orange", 
               "robots", 
               "move", 
               "around", 
               "the", 
               "wall", 
               "and", 
               "proceed", 
               "to", 
               "area", 
               "a"
            ], 
            "event_type": "voice_command", 
            "time": 320.55
         }, 
         {
            "command": [
               "and", 
               "red", 
               "robots", 
               "move", 
               "around", 
               "the", 
               "wall", 
               "and", 
               "proceed", 
               "to", 
               "area", 
               "b"
            ], 
            "event_type": "voice_command", 
            "time": 325.68
         }
      ], 
      "8": [
         {
            "command": [
               "robots", 
               "divide", 
               "yourselves", 
               "amongst", 
               "two", 
               "groups", 
               "half", 
               "and", 
               "half"
            ], 
            "event_type": "voice_command", 
            "time": 350.45
         }, 
         {
            "description": [
               "user", 
               "asked", 
               "for", 
               "clarification", 
               "about", 
               "whether", 
               "groups", 
               "should", 
               "be", 
               "equal"
            ], 
            "event_type": "memo"
         }, 
         {
            "description": [
               "user", 
               "expected", 
               "groups", 
               "to", 
               "be", 
               "parallel", 
               "to", 
               "each", 
               "other", 
               "e.g.", 
               "left", 
               "and", 
               "right"
            ], 
            "event_type": "memo"
         }
      ], 
      "9": [
         {
            "command": [
               "both", 
               "groups", 
               "merge"
            ], 
            "event_type": "voice_command", 
            "time": 378.11
         }
      ]
   }
}